vxvas2nets/__init__.py
vxvas2nets/vas2nets_sms.py
vxvas2nets/vas2nets_ussd.py
vxvas2nets/tests/__init__.py
vxvas2nets/tests/test_vas2nets_sms.py
vxvas2nets/tests/test_vas2nets_ussd.py
vxvas2nets-0.7.0.dist-info/DESCRIPTION.rst
vxvas2nets-0.7.0.dist-info/METADATA
vxvas2nets-0.7.0.dist-info/RECORD
vxvas2nets-0.7.0.dist-info/WHEEL
vxvas2nets-0.7.0.dist-info/metadata.json
vxvas2nets-0.7.0.dist-info/top_level.txt
