Metadata-Version: 2.0
Name: vxvas2nets
Version: 0.7.0
Summary: A Vas2Nets USSD transport for Vumi.
Home-page: http://github.com/praekelt/vumi-vas2nets
Author: Praekelt Foundation
Author-email: dev@praekeltfoundation.org
License: BSD
Platform: UNKNOWN
Classifier: Development Status :: 4 - Beta
Classifier: Intended Audience :: Developers
Classifier: License :: OSI Approved :: BSD License
Classifier: Operating System :: POSIX
Classifier: Programming Language :: Python
Classifier: Topic :: Software Development :: Libraries :: Python Modules
Classifier: Topic :: System :: Networking
Requires-Dist: treq
Requires-Dist: vumi (>=0.6.0)
